pLAtYpus_TNO/GRETA_tool.py
pLAtYpus_TNO/__init__.py
pLAtYpus_TNO/extra_plots.py
pLAtYpus_TNO/make_all_outputs.py
pLAtYpus_TNO/maps.py
pLAtYpus_TNO/pLAtYpus.py
pLAtYpus_TNO/process_survey_data.py
pLAtYpus_TNO/scores.py
pLAtYpus_TNO/solver.py
pLAtYpus_TNO/survey_to_pLAtYpus.py
pLAtYpus_TNO-1.0.5.dist-info/LICENCE
pLAtYpus_TNO-1.0.5.dist-info/METADATA
pLAtYpus_TNO-1.0.5.dist-info/WHEEL
pLAtYpus_TNO-1.0.5.dist-info/top_level.txt
pLAtYpus_TNO-1.0.5.dist-info/RECORD
