Metadata-Version: 2.1
Name: pLAtYpus-TNO
Version: 1.0.5
Summary: The pLAtYpus model for engagement levels of stakeholders
Author-email: Omar Usmani and Carlos Montalvo <Omar.Usmani@TNO.nl>
Project-URL: Homepage, https://github.com/TNO/pLAtYpus
Classifier: Programming Language :: Python :: 3
Classifier: License :: OSI Approved :: Apache Software License
Classifier: Operating System :: OS Independent
Requires-Python: >=3.8
License-File: LICENCE
Requires-Dist: attrs ==23.1.0
Requires-Dist: beautifulsoup4 ==4.12.2
Requires-Dist: blinker ==1.6.2
Requires-Dist: blosc2 ==2.0.0
Requires-Dist: build ==1.0.3
Requires-Dist: cdsapi ==0.6.1
Requires-Dist: certifi ==2023.7.22
Requires-Dist: cffi ==1.15.1
Requires-Dist: cfgrib ==0.9.10.4
Requires-Dist: charset-normalizer ==3.2.0
Requires-Dist: click ==8.1.6
Requires-Dist: click-plugins ==1.1.1
Requires-Dist: cligj ==0.7.2
Requires-Dist: colorama ==0.4.6
Requires-Dist: contourpy ==1.1.0
Requires-Dist: cycler ==0.11.0
Requires-Dist: Cython ==3.0.0
Requires-Dist: dash ==2.9.3
Requires-Dist: dash-core-components ==2.0.0
Requires-Dist: dash-html-components ==2.0.0
Requires-Dist: dash-table ==5.0.0
Requires-Dist: docutils ==0.20.1
Requires-Dist: eccodes ==1.6.0
Requires-Dist: ecmwflibs ==0.5.1
Requires-Dist: et-xmlfile ==1.1.0
Requires-Dist: ETS-CookBook ==1.0.4
Requires-Dist: findlibs ==0.0.5
Requires-Dist: Fiona ==1.9.4.post1
Requires-Dist: Flask ==2.3.2
Requires-Dist: fonttools ==4.41.1
Requires-Dist: geopandas ==0.13.2
Requires-Dist: idna ==3.4
Requires-Dist: importlib-metadata ==6.8.0
Requires-Dist: itsdangerous ==2.1.2
Requires-Dist: jaraco.classes ==3.3.0
Requires-Dist: Jinja2 ==3.1.2
Requires-Dist: keyring ==24.2.0
Requires-Dist: kiwisolver ==1.4.4
Requires-Dist: lxml ==4.9.3
Requires-Dist: markdown-it-py ==3.0.0
Requires-Dist: MarkupSafe ==2.1.3
Requires-Dist: matplotlib ==3.7.2
Requires-Dist: mdurl ==0.1.2
Requires-Dist: more-itertools ==10.1.0
Requires-Dist: msgpack ==1.0.5
Requires-Dist: nh3 ==0.2.14
Requires-Dist: numexpr ==2.8.4
Requires-Dist: numpy ==1.24.3
Requires-Dist: openpyxl ==3.1.2
Requires-Dist: packaging ==23.1
Requires-Dist: pandas ==2.0.1
Requires-Dist: Pillow ==10.0.0
Requires-Dist: pkginfo ==1.9.6
Requires-Dist: plotly ==5.14.1
Requires-Dist: py-cpuinfo ==9.0.0
Requires-Dist: pyarrow ==12.0.1
Requires-Dist: pycodestyle ==2.11.0
Requires-Dist: pycparser ==2.21
Requires-Dist: Pygments ==2.16.1
Requires-Dist: pyparsing ==3.0.9
Requires-Dist: pyproj ==3.6.0
Requires-Dist: pyproject-hooks ==1.0.0
Requires-Dist: python-dateutil ==2.8.2
Requires-Dist: pytz ==2023.3
Requires-Dist: pywin32-ctypes ==0.2.2
Requires-Dist: readme-renderer ==42.0
Requires-Dist: requests ==2.31.0
Requires-Dist: requests-toolbelt ==1.0.0
Requires-Dist: rfc3986 ==2.0.0
Requires-Dist: rich ==13.6.0
Requires-Dist: scipy ==1.10.1
Requires-Dist: shapely ==2.0.1
Requires-Dist: six ==1.16.0
Requires-Dist: soupsieve ==2.4.1
Requires-Dist: tables ==3.8.0
Requires-Dist: tenacity ==8.2.2
Requires-Dist: tqdm ==4.65.0
Requires-Dist: twine ==4.0.2
Requires-Dist: tzdata ==2023.3
Requires-Dist: urllib3 ==2.0.4
Requires-Dist: Werkzeug ==2.3.4
Requires-Dist: xarray ==2023.7.0
Requires-Dist: zipp ==3.17.0
